{"title":"벅스 ─ 최신 음악 ─ 앨범 ─ 주목","url":"https://music.bugs.co.kr/newest/album/totalpicked","favicon":"https://file.bugsm.co.kr/wbugs/common/faviconBugs.ico","elements":[{"title":"PIECE-7 : 온시(on_poem)","contents":"<p class=\"artist\">\n<a href=\"https://music.bugs.co.kr/artist/80353865?wl_ref=list_ab_04\" class=\"artistTitle\" title=\"THE PIECES(더 피스)\" onclick=\"\n\" target=\"_self\">THE PIECES(더 피스)</a>\n</p>\n<p>\n<time datetime=\"\">2023.05.10</time>\n<span class=\"albumType\">싱글</span>\n</p>","link":"https://music.bugs.co.kr/album/4086324?wl_ref=list_ab_03","retrieved":1683688692449,"image":"https://image.bugsm.co.kr/album/images/170/40863/4086324.jpg?version=20230510120026.0"},{"title":"알고보니 혼수상태 가요제 우승자 특전곡","contents":"<p class=\"artist\">\n<a href=\"https://music.bugs.co.kr/artist/19169?wl_ref=list_ab_04\" class=\"artistTitle\" title=\"박서진\" onclick=\"\n\" target=\"_self\">박서진</a>\n</p>\n<p>\n<time datetime=\"\">2023.05.10</time>\n<span class=\"albumType\">싱글</span>\n</p>","link":"https://music.bugs.co.kr/album/4086329?wl_ref=list_ab_03","retrieved":1683688692449,"image":"https://image.bugsm.co.kr/album/images/170/40863/4086329.jpg?version=20230510120026.0"},{"title":"나 정말 힘들어 Part.2","contents":"<p class=\"artist\">\n<a href=\"https://music.bugs.co.kr/artist/20062551?wl_ref=list_ab_04\" class=\"artistTitle\" title=\"정창룡\" onclick=\"\n\" target=\"_self\">정창룡</a>\n</p>\n<p>\n<time datetime=\"\">2023.05.09</time>\n<span class=\"albumType\">싱글</span>\n</p>","link":"https://music.bugs.co.kr/album/4086275?wl_ref=list_ab_03","retrieved":1683623799147,"image":"https://image.bugsm.co.kr/album/images/170/40862/4086275.jpg?version=20230509180021.0"},{"title":"돌 아 오 지 마","contents":"<p class=\"artist\">\n<a href=\"https://music.bugs.co.kr/artist/20088878?wl_ref=list_ab_04\" class=\"artistTitle\" title=\"Mingginyu (밍기뉴)\" onclick=\"\n\" target=\"_self\">Mingginyu (밍기뉴)</a>\n</p>\n<p>\n<time datetime=\"\">2023.05.10</time>\n<span class=\"albumType\">싱글</span>\n</p>","link":"https://music.bugs.co.kr/album/20563782?wl_ref=list_ab_03","retrieved":1683688692450,"image":"https://image.bugsm.co.kr/album/images/170/205637/20563782.jpg?version=20230510120026.0"},{"title":"이별이 참 아프니까","contents":"<p class=\"artist\">\n<a href=\"https://music.bugs.co.kr/artist/80182216?wl_ref=list_ab_04\" class=\"artistTitle\" title=\"여은\" onclick=\"\n\" target=\"_self\">여은</a>\n</p>\n<p>\n<time datetime=\"\">2023.05.10</time>\n<span class=\"albumType\">싱글</span>\n</p>","link":"https://music.bugs.co.kr/album/20564602?wl_ref=list_ab_03","retrieved":1683688692450,"image":"https://image.bugsm.co.kr/album/images/170/205646/20564602.jpg?version=20230510120026.0"},{"title":"말해주라","contents":"<p class=\"artist\">\n<a href=\"https://music.bugs.co.kr/artist/80132726?wl_ref=list_ab_04\" class=\"artistTitle\" title=\"소수빈\" onclick=\"\n\" target=\"_self\">소수빈</a>\n</p>\n<p>\n<time datetime=\"\">2023.05.10</time>\n<span class=\"albumType\">싱글</span>\n</p>","link":"https://music.bugs.co.kr/album/4086330?wl_ref=list_ab_03","retrieved":1683688692454,"image":"https://image.bugsm.co.kr/album/images/170/40863/4086330.jpg?version=20230510120026.0"},{"title":"에루화","contents":"<p class=\"artist\">\n<a href=\"https://music.bugs.co.kr/artist/80199948?wl_ref=list_ab_04\" class=\"artistTitle\" title=\"양반들 (Yangbans)\" onclick=\"\n\" target=\"_self\">양반들 (Yangbans)</a>\n</p>\n<p>\n<time datetime=\"\">2023.05.10</time>\n<span class=\"albumType\">EP(미니)</span>\n</p>","link":"https://music.bugs.co.kr/album/20563164?wl_ref=list_ab_03","retrieved":1683688692454,"image":"https://image.bugsm.co.kr/album/images/170/205631/20563164.jpg?version=20230510120026.0"},{"title":"아이마미따(Ay Mamita)","contents":"<p class=\"artist\">\n<!-- a tag title -->\n<a href=\"https://music.bugs.co.kr/artist/9751?wl_ref=list_ab_04\" class=\"artistTitle\" title=\"유준상\">유준상</a>\n<!-- a tag link -->\n<a href=\"javascript:void(0);\" name=\"atag_martist_list\" class=\"more\" title=\"아티스트 전체보기\" wise_log_str=\"?wl_ref=list_ab_04\" onclick=\"bugs.layermenu.openMultiArtistSearchResultPopLayer(this, '유준상||유준상||9751||OK\\\\n로민||로민||80342016||OK\\\\n원준||원준||80342020||OK', ''); return false;\">\n유준상\n</a> </p>\n<p>\n<time datetime=\"\">2023.05.10</time>\n<span class=\"albumType\">싱글</span>\n</p>","link":"https://music.bugs.co.kr/album/20564155?wl_ref=list_ab_03","retrieved":1683688692455,"image":"https://image.bugsm.co.kr/album/images/170/205641/20564155.jpg?version=20230510120001.0"},{"title":"Lonely man but sweet man","contents":"<p class=\"artist\">\n<a href=\"https://music.bugs.co.kr/artist/80321936?wl_ref=list_ab_04\" class=\"artistTitle\" title=\"최항석과 부기몬스터\" onclick=\"\n\" target=\"_self\">최항석과 부기몬스터</a>\n</p>\n<p>\n<time datetime=\"\">2023.05.10</time>\n<span class=\"albumType\">EP(미니)</span>\n</p>","link":"https://music.bugs.co.kr/album/31654762?wl_ref=list_ab_03","retrieved":1683688692456,"image":"https://image.bugsm.co.kr/album/images/170/316547/31654762.jpg?version=20230510120026.0"},{"title":"하루종일","contents":"<p class=\"artist\">\n<a href=\"https://music.bugs.co.kr/artist/20114494?wl_ref=list_ab_04\" class=\"artistTitle\" title=\"서로이\" onclick=\"\n\" target=\"_self\">서로이</a>\n</p>\n<p>\n<time datetime=\"\">2023.05.10</time>\n<span class=\"albumType\">싱글</span>\n</p>","link":"https://music.bugs.co.kr/album/20564607?wl_ref=list_ab_03","retrieved":1683688692462,"image":"https://image.bugsm.co.kr/album/images/170/205646/20564607.jpg?version=20230510120026.0"},{"title":"MBC 일일드라마 '하늘의 인연' OST Part.2","contents":"<p class=\"artist\">\n<a href=\"https://music.bugs.co.kr/artist/80053405?wl_ref=list_ab_04\" class=\"artistTitle\" title=\"숙희\" onclick=\"\n\" target=\"_self\">숙희</a>\n</p>\n<p>\n<time datetime=\"\">2023.05.10</time>\n<span class=\"albumType\">OST</span>\n</p>","link":"https://music.bugs.co.kr/album/20564710?wl_ref=list_ab_03","retrieved":1683688692463,"image":"https://image.bugsm.co.kr/album/images/170/205647/20564710.jpg?version=20230510120026.0"},{"title":"glitter eyes","contents":"<p class=\"artist\">\n<a href=\"https://music.bugs.co.kr/artist/20087989?wl_ref=list_ab_04\" class=\"artistTitle\" title=\"SEINY\" onclick=\"\n\" target=\"_self\">SEINY</a>\n</p>\n<p>\n<time datetime=\"\">2023.05.10</time>\n<span class=\"albumType\">싱글</span>\n</p>","link":"https://music.bugs.co.kr/album/4086302?wl_ref=list_ab_03","retrieved":1683688692464,"image":"https://image.bugsm.co.kr/album/images/170/40863/4086302.jpg?version=20230510120026.0"},{"title":"Life In LA","contents":"<p class=\"artist\">\n<!-- a tag title -->\n<a href=\"https://music.bugs.co.kr/artist/20185079?wl_ref=list_ab_04\" class=\"artistTitle\" title=\"Mix.audio\">Mix.audio</a>\n<!-- a tag link -->\n<a href=\"javascript:void(0);\" name=\"atag_martist_list\" class=\"more\" title=\"아티스트 전체보기\" wise_log_str=\"?wl_ref=list_ab_04\" onclick=\"bugs.layermenu.openMultiArtistSearchResultPopLayer(this, 'Mix.audio||Mix.audio||20185079||OK\\\\nDbo||Dbo (디보)||80218657||OK', ''); return false;\">\nMix.audio\n</a> </p>\n<p>\n<time datetime=\"\">2023.05.10</time>\n<span class=\"albumType\">싱글</span>\n</p>","link":"https://music.bugs.co.kr/album/20563996?wl_ref=list_ab_03","retrieved":1683688692464,"image":"https://image.bugsm.co.kr/album/images/170/205639/20563996.jpg?version=20230510120026.0"},{"title":"아님말고","contents":"<p class=\"artist\">\n<a href=\"https://music.bugs.co.kr/artist/12766508?wl_ref=list_ab_04\" class=\"artistTitle\" title=\"썹 (Ssup)\" onclick=\"\n\" target=\"_self\">썹 (Ssup)</a>\n</p>\n<p>\n<time datetime=\"\">2023.05.10</time>\n<span class=\"albumType\">싱글</span>\n</p>","link":"https://music.bugs.co.kr/album/20564244?wl_ref=list_ab_03","retrieved":1683688692466,"image":"https://image.bugsm.co.kr/album/images/170/205642/20564244.jpg?version=20230510120026.0"},{"title":"STAY","contents":"<p class=\"artist\">\n<a href=\"https://music.bugs.co.kr/artist/20012581?wl_ref=list_ab_04\" class=\"artistTitle\" title=\"아웃오브캠퍼스\" onclick=\"\n\" target=\"_self\">아웃오브캠퍼스</a>\n</p>\n<p>\n<time datetime=\"\">2023.05.10</time>\n<span class=\"albumType\">싱글</span>\n</p>","link":"https://music.bugs.co.kr/album/20564590?wl_ref=list_ab_03","retrieved":1683688692473,"image":"https://image.bugsm.co.kr/album/images/170/205645/20564590.jpg?version=20230510120026.0"},{"title":"ACCESS","contents":"<p class=\"artist\">\n<a href=\"https://music.bugs.co.kr/artist/80382070?wl_ref=list_ab_04\" class=\"artistTitle\" title=\"XXOK\" onclick=\"\n\" target=\"_self\">XXOK</a>\n</p>\n<p>\n<time datetime=\"\">2023.05.10</time>\n<span class=\"albumType\">싱글</span>\n</p>","link":"https://music.bugs.co.kr/album/4086318?wl_ref=list_ab_03","retrieved":1683688692473,"image":"https://image.bugsm.co.kr/album/images/170/40863/4086318.jpg?version=20230510120026.0"},{"title":"Soldier","contents":"<p class=\"artist\">\n<a href=\"https://music.bugs.co.kr/artist/80108330?wl_ref=list_ab_04\" class=\"artistTitle\" title=\"윌리엄 손\" onclick=\"\n\" target=\"_self\">윌리엄 손</a>\n</p>\n<p>\n<time datetime=\"\">2023.05.10</time>\n<span class=\"albumType\">싱글</span>\n</p>","link":"https://music.bugs.co.kr/album/20564901?wl_ref=list_ab_03","retrieved":1683688692473,"image":"https://image.bugsm.co.kr/album/images/170/205649/20564901.jpg?version=20230510120026.0"},{"title":"그렇게 이별","contents":"<p class=\"artist\">\n<a href=\"https://music.bugs.co.kr/artist/80119762?wl_ref=list_ab_04\" class=\"artistTitle\" title=\"카페모카\" onclick=\"\n\" target=\"_self\">카페모카</a>\n</p>\n<p>\n<time datetime=\"\">2023.05.10</time>\n<span class=\"albumType\">싱글</span>\n</p>","link":"https://music.bugs.co.kr/album/20564224?wl_ref=list_ab_03","retrieved":1683688692473,"image":"https://image.bugsm.co.kr/album/images/170/205642/20564224.jpg?version=20230510120026.0"},{"title":"자장가","contents":"<p class=\"artist\">\n<a href=\"https://music.bugs.co.kr/artist/20179550?wl_ref=list_ab_04\" class=\"artistTitle\" title=\"이주영\" onclick=\"\n\" target=\"_self\">이주영</a>\n</p>\n<p>\n<time datetime=\"\">2023.05.10</time>\n<span class=\"albumType\">싱글</span>\n</p>","link":"https://music.bugs.co.kr/album/20564513?wl_ref=list_ab_03","retrieved":1683688692473,"image":"https://image.bugsm.co.kr/album/images/170/205645/20564513.jpg?version=20230510120026.0"},{"title":"혼자 (Alone)","contents":"<p class=\"artist\">\n<a href=\"https://music.bugs.co.kr/artist/1924?wl_ref=list_ab_04\" class=\"artistTitle\" title=\"강승모\" onclick=\"\n\" target=\"_self\">강승모</a>\n</p>\n<p>\n<time datetime=\"\">2023.05.10</time>\n<span class=\"albumType\">싱글</span>\n</p>","link":"https://music.bugs.co.kr/album/20564427?wl_ref=list_ab_03","retrieved":1683688692474,"image":"https://image.bugsm.co.kr/album/images/170/205644/20564427.jpg?version=20230510120026.0"},{"title":"Thinking or feeling? (T vs F)","contents":"<p class=\"artist\">\n<a href=\"https://music.bugs.co.kr/artist/20115192?wl_ref=list_ab_04\" class=\"artistTitle\" title=\"피아컬(PIACAL)\" onclick=\"\n\" target=\"_self\">피아컬(PIACAL)</a>\n</p>\n<p>\n<time datetime=\"\">2023.05.10</time>\n<span class=\"albumType\">싱글</span>\n</p>","link":"https://music.bugs.co.kr/album/20564026?wl_ref=list_ab_03","retrieved":1683688692476,"image":"https://image.bugsm.co.kr/album/images/170/205640/20564026.jpg?version=20230510120026.0"},{"title":"And I","contents":"<p class=\"artist\">\n<a href=\"https://music.bugs.co.kr/artist/20081050?wl_ref=list_ab_04\" class=\"artistTitle\" title=\"hu57la\" onclick=\"\n\" target=\"_self\">hu57la</a>\n</p>\n<p>\n<time datetime=\"\">2023.05.10</time>\n<span class=\"albumType\">싱글</span>\n</p>","link":"https://music.bugs.co.kr/album/20564725?wl_ref=list_ab_03","retrieved":1683688692476,"image":"https://image.bugsm.co.kr/album/images/170/205647/20564725.jpg?version=20230510120026.0"},{"title":"머무르곤","contents":"<p class=\"artist\">\n<a href=\"https://music.bugs.co.kr/artist/20144768?wl_ref=list_ab_04\" class=\"artistTitle\" title=\"연희\" onclick=\"\n\" target=\"_self\">연희</a>\n</p>\n<p>\n<time datetime=\"\">2023.05.10</time>\n<span class=\"albumType\">싱글</span>\n</p>","link":"https://music.bugs.co.kr/album/20564630?wl_ref=list_ab_03","retrieved":1683688692479,"image":"https://image.bugsm.co.kr/album/images/170/205646/20564630.jpg?version=20230510120026.0"},{"title":"9PM IN SEOUL (SLANG FREESTYLE)","contents":"<p class=\"artist\">\n<a href=\"https://music.bugs.co.kr/artist/20097769?wl_ref=list_ab_04\" class=\"artistTitle\" title=\"Digital Dav\" onclick=\"\n\" target=\"_self\">Digital Dav</a>\n</p>\n<p>\n<time datetime=\"\">2023.05.10</time>\n<span class=\"albumType\">싱글</span>\n</p>","link":"https://music.bugs.co.kr/album/20564346?wl_ref=list_ab_03","retrieved":1683688692480,"image":"https://image.bugsm.co.kr/album/images/170/205643/20564346.jpg?version=20230510120026.0"},{"title":"큐피트 화살에 꽂히면 이런 기분일까","contents":"<p class=\"artist\">\n<a href=\"https://music.bugs.co.kr/artist/20185927?wl_ref=list_ab_04\" class=\"artistTitle\" title=\"리루 (Riru)\" onclick=\"\n\" target=\"_self\">리루 (Riru)</a>\n</p>\n<p>\n<time datetime=\"\">2023.05.10</time>\n<span class=\"albumType\">싱글</span>\n</p>","link":"https://music.bugs.co.kr/album/20564727?wl_ref=list_ab_03","retrieved":1683688692480,"image":"https://image.bugsm.co.kr/album/images/170/205647/20564727.jpg?version=20230510120026.0"},{"title":"사랑니","contents":"<p class=\"artist\">\n<a href=\"https://music.bugs.co.kr/artist/20110086?wl_ref=list_ab_04\" class=\"artistTitle\" title=\"kingeunsan(킹근산)\" onclick=\"\n\" target=\"_self\">kingeunsan(킹근산)</a>\n</p>\n<p>\n<time datetime=\"\">2023.05.10</time>\n<span class=\"albumType\">싱글</span>\n</p>","link":"https://music.bugs.co.kr/album/20564743?wl_ref=list_ab_03","retrieved":1683688692486,"image":"https://image.bugsm.co.kr/album/images/170/205647/20564743.jpg?version=20230510120026.0"},{"title":"나의스물","contents":"<p class=\"artist\">\n<a href=\"https://music.bugs.co.kr/artist/20118473?wl_ref=list_ab_04\" class=\"artistTitle\" title=\"블랑 (Blanc)\" onclick=\"\n\" target=\"_self\">블랑 (Blanc)</a>\n</p>\n<p>\n<time datetime=\"\">2023.05.10</time>\n<span class=\"albumType\">싱글</span>\n</p>","link":"https://music.bugs.co.kr/album/20564784?wl_ref=list_ab_03","retrieved":1683688692508,"image":"https://image.bugsm.co.kr/album/images/170/205647/20564784.jpg?version=20230510120026.0"},{"title":"그렇게 시작된 우리","contents":"<p class=\"artist\">\n<a href=\"https://music.bugs.co.kr/artist/80172674?wl_ref=list_ab_04\" class=\"artistTitle\" title=\"Mr. 페페\" onclick=\"\n\" target=\"_self\">Mr. 페페</a>\n</p>\n<p>\n<time datetime=\"\">2023.05.10</time>\n<span class=\"albumType\">EP(미니)</span>\n</p>","link":"https://music.bugs.co.kr/album/20564493?wl_ref=list_ab_03","retrieved":1683688692513,"image":"https://image.bugsm.co.kr/album/images/170/205644/20564493.jpg?version=20230510120026.0"},{"title":"Fly Away","contents":"<p class=\"artist\">\n<a href=\"https://music.bugs.co.kr/artist/80330601?wl_ref=list_ab_04\" class=\"artistTitle\" title=\"AB6IX (에이비식스)\" onclick=\"\n\" target=\"_self\">AB6IX (에이비식스)</a>\n</p>\n<p>\n<time datetime=\"\">2023.05.10</time>\n<span class=\"albumType\">싱글</span>\n</p>","link":"https://music.bugs.co.kr/album/4086326?wl_ref=list_ab_03","retrieved":1683688692515,"image":"https://image.bugsm.co.kr/album/images/170/40863/4086326.jpg?version=20230510013101.0"},{"title":"don’t call me pretty","contents":"<p class=\"artist\">\n<a href=\"https://music.bugs.co.kr/artist/80078104?wl_ref=list_ab_04\" class=\"artistTitle\" title=\"GAYLE\" onclick=\"\n\" target=\"_self\">GAYLE</a>\n</p>\n<p>\n<time datetime=\"\">2023.05.05</time>\n<span class=\"albumType\">싱글</span>\n</p>","link":"https://music.bugs.co.kr/album/31646990?wl_ref=list_ab_03","retrieved":1683688692517,"image":"https://image.bugsm.co.kr/album/images/170/316469/31646990.jpg?version=20230506070120.0"},{"title":"The Chant (For Club Play Only, Pt. 8)","contents":"<p class=\"artist\">\n<a href=\"https://music.bugs.co.kr/artist/80133185?wl_ref=list_ab_04\" class=\"artistTitle\" title=\"Duke Dumont(듀크 듀몬트)\" onclick=\"\n\" target=\"_self\">Duke Dumont(듀크 듀몬트)</a>\n</p>\n<p>\n<time datetime=\"\">2023.05.05</time>\n<span class=\"albumType\">싱글</span>\n</p>","link":"https://music.bugs.co.kr/album/31651949?wl_ref=list_ab_03","retrieved":1683688692521,"image":"https://image.bugsm.co.kr/album/images/170/316519/31651949.jpg?version=20230510031217.0"},{"title":"Angel Arms","contents":"<p class=\"artist\">\n<a href=\"https://music.bugs.co.kr/artist/12275630?wl_ref=list_ab_04\" class=\"artistTitle\" title=\"August Royals\" onclick=\"\n\" target=\"_self\">August Royals</a>\n</p>\n<p>\n<time datetime=\"\">2023.05.05</time>\n<span class=\"albumType\">싱글</span>\n</p>","link":"https://music.bugs.co.kr/album/31634176?wl_ref=list_ab_03","retrieved":1683688692521,"image":"https://image.bugsm.co.kr/album/images/170/316341/31634176.jpg?version=20230506065055.0"},{"title":"What's That?","contents":"<p class=\"artist\">\n<a href=\"https://music.bugs.co.kr/artist/80274531?wl_ref=list_ab_04\" class=\"artistTitle\" title=\"Joyner Lucas\" onclick=\"\n\" target=\"_self\">Joyner Lucas</a>\n</p>\n<p>\n<time datetime=\"\">2023.05.09</time>\n<span class=\"albumType\">싱글</span>\n</p>","link":"https://music.bugs.co.kr/album/31643208?wl_ref=list_ab_03","retrieved":1683688692529,"image":"https://image.bugsm.co.kr/album/images/170/316432/31643208.jpg?version=20230510063524.0"},{"title":"C.h.a.o.s.m.y.t.h.","contents":"<p class=\"artist\">\n<a href=\"https://music.bugs.co.kr/artist/80013537?wl_ref=list_ab_04\" class=\"artistTitle\" title=\"예성 (YESUNG)\" onclick=\"\n\" target=\"_self\">예성 (YESUNG)</a>\n</p>\n<p>\n<time datetime=\"\">2023.05.10</time>\n<span class=\"albumType\">싱글</span>\n</p>","link":"https://music.bugs.co.kr/album/20564613?wl_ref=list_ab_03","retrieved":1683688692531,"image":"https://image.bugsm.co.kr/album/images/170/205646/20564613.jpg?version=20230510000024.0"},{"title":"Hunger","contents":"<p class=\"artist\">\n<a href=\"https://music.bugs.co.kr/artist/10721840?wl_ref=list_ab_04\" class=\"artistTitle\" title=\"TheFatRat\" onclick=\"\n\" target=\"_self\">TheFatRat</a>\n</p>\n<p>\n<time datetime=\"\">2023.05.10</time>\n<span class=\"albumType\">싱글</span>\n</p>","link":"https://music.bugs.co.kr/album/20563658?wl_ref=list_ab_03","retrieved":1683688692532,"image":"https://image.bugsm.co.kr/album/images/170/205636/20563658.jpg?version=20230510120026.0"},{"title":"touching myself","contents":"<p class=\"artist\">\n<a href=\"https://music.bugs.co.kr/artist/80306350?wl_ref=list_ab_04\" class=\"artistTitle\" title=\"laye\" onclick=\"\n\" target=\"_self\">laye</a>\n</p>\n<p>\n<time datetime=\"\">2023.05.05</time>\n<span class=\"albumType\">싱글</span>\n</p>","link":"https://music.bugs.co.kr/album/31652750?wl_ref=list_ab_03","retrieved":1683688692532,"image":"https://image.bugsm.co.kr/album/images/170/316527/31652750.jpg?version=20230506064314.0"},{"title":"Lose You (Felix Jaehn Remix)","contents":"<p class=\"artist\">\n<a href=\"https://music.bugs.co.kr/artist/80147640?wl_ref=list_ab_04\" class=\"artistTitle\" title=\"Sam Smith(샘 스미스)\" onclick=\"\n\" target=\"_self\">Sam Smith(샘 스미스)</a>\n</p>\n<p>\n<time datetime=\"\">2023.05.05</time>\n<span class=\"albumType\">싱글</span>\n</p>","link":"https://music.bugs.co.kr/album/31651961?wl_ref=list_ab_03","retrieved":1683688692533,"image":"https://image.bugsm.co.kr/album/images/170/316519/31651961.jpg?version=20230510032223.0"},{"title":"詩 (Shh)","contents":"<p class=\"artist\">\n<a href=\"https://music.bugs.co.kr/artist/80269668?wl_ref=list_ab_04\" class=\"artistTitle\" title=\"펜타곤\" onclick=\"\n\" target=\"_self\">펜타곤</a>\n</p>\n<p>\n<time datetime=\"\">2023.05.10</time>\n<span class=\"albumType\">싱글</span>\n</p>","link":"https://music.bugs.co.kr/album/4086316?wl_ref=list_ab_03","retrieved":1683688692534,"image":"https://image.bugsm.co.kr/album/images/170/40863/4086316.jpg?version=20230510022429.0"},{"title":"About To Happen","contents":"<p class=\"artist\">\n<a href=\"https://music.bugs.co.kr/artist/20033308?wl_ref=list_ab_04\" class=\"artistTitle\" title=\"Oh The Larceny\" onclick=\"\n\" target=\"_self\">Oh The Larceny</a>\n</p>\n<p>\n<time datetime=\"\">2023.05.10</time>\n<span class=\"albumType\">EP(미니)</span>\n</p>","link":"https://music.bugs.co.kr/album/20562323?wl_ref=list_ab_03","retrieved":1683688692543,"image":"https://image.bugsm.co.kr/album/images/170/205623/20562323.jpg?version=20230510120026.0"},{"title":"Big Brown Eyes","contents":"<p class=\"artist\">\n<a href=\"https://music.bugs.co.kr/artist/12070460?wl_ref=list_ab_04\" class=\"artistTitle\" title=\"Myles Cameron\" onclick=\"\n\" target=\"_self\">Myles Cameron</a>\n</p>\n<p>\n<time datetime=\"\">2023.05.05</time>\n<span class=\"albumType\">싱글</span>\n</p>","link":"https://music.bugs.co.kr/album/20563986?wl_ref=list_ab_03","retrieved":1683688692543,"image":"https://image.bugsm.co.kr/album/images/170/205639/20563986.jpg?version=20230505002234.0"},{"title":"The Drift","contents":"<p class=\"artist\">\n<a href=\"https://music.bugs.co.kr/artist/20106468?wl_ref=list_ab_04\" class=\"artistTitle\" title=\"미란이 (MIRANI)\" onclick=\"\n\" target=\"_self\">미란이 (MIRANI)</a>\n</p>\n<p>\n<time datetime=\"\">2023.05.09</time>\n<span class=\"albumType\">정규</span>\n</p>","link":"https://music.bugs.co.kr/album/4086315?wl_ref=list_ab_03","retrieved":1683623799165,"image":"https://image.bugsm.co.kr/album/images/170/40863/4086315.jpg?version=20230510033352.0"},{"title":"잠깐 시간 될까","contents":"<p class=\"artist\">\n<a href=\"https://music.bugs.co.kr/artist/20056684?wl_ref=list_ab_04\" class=\"artistTitle\" title=\"이무진\" onclick=\"\n\" target=\"_self\">이무진</a>\n</p>\n<p>\n<time datetime=\"\">2023.05.09</time>\n<span class=\"albumType\">싱글</span>\n</p>","link":"https://music.bugs.co.kr/album/4086287?wl_ref=list_ab_03","retrieved":1683623799172,"image":"https://image.bugsm.co.kr/album/images/170/40862/4086287.jpg?version=20230510064245.0"},{"title":"ADYA","contents":"<p class=\"artist\">\n<a href=\"https://music.bugs.co.kr/artist/20185680?wl_ref=list_ab_04\" class=\"artistTitle\" title=\"ADYA (에이디야)\" onclick=\"\n\" target=\"_self\">ADYA (에이디야)</a>\n</p>\n<p>\n<time datetime=\"\">2023.05.09</time>\n<span class=\"albumType\">싱글</span>\n</p>","link":"https://music.bugs.co.kr/album/20563938?wl_ref=list_ab_03","retrieved":1683623799174,"image":"https://image.bugsm.co.kr/album/images/170/205639/20563938.jpg?version=20230510013851.0"},{"title":"Fault","contents":"<p class=\"artist\">\n<a href=\"https://music.bugs.co.kr/artist/80236471?wl_ref=list_ab_04\" class=\"artistTitle\" title=\"리피트 (Repeat)\" onclick=\"\n\" target=\"_self\">리피트 (Repeat)</a>\n</p>\n<p>\n<time datetime=\"\">2023.05.09</time>\n<span class=\"albumType\">싱글</span>\n</p>","link":"https://music.bugs.co.kr/album/4086267?wl_ref=list_ab_03","retrieved":1683602311829,"image":"https://image.bugsm.co.kr/album/images/170/40862/4086267.jpg?version=20230510020541.0"},{"title":"ALWAYS","contents":"<p class=\"artist\">\n<a href=\"https://music.bugs.co.kr/artist/13191104?wl_ref=list_ab_04\" class=\"artistTitle\" title=\"XODIAC\" onclick=\"\n\" target=\"_self\">XODIAC</a>\n</p>\n<p>\n<time datetime=\"\">2023.05.09</time>\n<span class=\"albumType\">싱글</span>\n</p>","link":"https://music.bugs.co.kr/album/31654783?wl_ref=list_ab_03","retrieved":1683623799185,"image":"https://image.bugsm.co.kr/album/images/170/316547/31654783.jpg?version=20230510102502.0"},{"title":"CHO","contents":"<p class=\"artist\">\n<a href=\"https://music.bugs.co.kr/artist/13259223?wl_ref=list_ab_04\" class=\"artistTitle\" title=\"Feverse(피버스)\" onclick=\"\n\" target=\"_self\">Feverse(피버스)</a>\n</p>\n<p>\n<time datetime=\"\">2023.05.09</time>\n<span class=\"albumType\">EP(미니)</span>\n</p>","link":"https://music.bugs.co.kr/album/4086283?wl_ref=list_ab_03","retrieved":1683623799185,"image":"https://image.bugsm.co.kr/album/images/170/40862/4086283.jpg?version=20230510064242.0"},{"title":"어쩌다 마주친, 그대 OST Part. 2","contents":"<p class=\"artist\">\n<a href=\"https://music.bugs.co.kr/artist/8008540?wl_ref=list_ab_04\" class=\"artistTitle\" title=\"쿨 이재훈\" onclick=\"\n\" target=\"_self\">쿨 이재훈</a>\n</p>\n<p>\n<time datetime=\"\">2023.05.09</time>\n<span class=\"albumType\">OST</span>\n</p>","link":"https://music.bugs.co.kr/album/20564379?wl_ref=list_ab_03","retrieved":1683623799186,"image":"https://image.bugsm.co.kr/album/images/170/205643/20564379.jpg?version=20230509180019.0"},{"title":"UNDER SEONGSU BRIDGE II","contents":"<p class=\"artist\">\n<a href=\"https://music.bugs.co.kr/artist/20125384?wl_ref=list_ab_04\" class=\"artistTitle\" title=\"UNDER SEONGSU BRIDGE\" onclick=\"\n\" target=\"_self\">UNDER SEONGSU BRIDGE</a>\n</p>\n<p>\n<time datetime=\"\">2023.05.09</time>\n<span class=\"albumType\">정규</span>\n</p>","link":"https://music.bugs.co.kr/album/4086290?wl_ref=list_ab_03","retrieved":1683623799186,"image":"https://image.bugsm.co.kr/album/images/170/40862/4086290.jpg?version=20230510064243.0"},{"title":"너를 위한 별이 될게","contents":"<p class=\"artist\">\n<a href=\"https://music.bugs.co.kr/artist/80330253?wl_ref=list_ab_04\" class=\"artistTitle\" title=\"한빈(포맨)\" onclick=\"\n\" target=\"_self\">한빈(포맨)</a>\n</p>\n<p>\n<time datetime=\"\">2023.05.09</time>\n<span class=\"albumType\">싱글</span>\n</p>","link":"https://music.bugs.co.kr/album/20563599?wl_ref=list_ab_03","retrieved":1683623799190,"image":"https://image.bugsm.co.kr/album/images/170/205635/20563599.jpg?version=20230510034849.0"},{"title":"Feat.","contents":"<p class=\"artist\">\n<a href=\"https://music.bugs.co.kr/artist/20105637?wl_ref=list_ab_04\" class=\"artistTitle\" title=\"여지영\" onclick=\"\n\" target=\"_self\">여지영</a>\n</p>\n<p>\n<time datetime=\"\">2023.05.09</time>\n<span class=\"albumType\">정규</span>\n</p>","link":"https://music.bugs.co.kr/album/20564534?wl_ref=list_ab_03","retrieved":1683623799191,"image":"https://image.bugsm.co.kr/album/images/170/205645/20564534.jpg?version=20230509180021.0"},{"title":"hustlin'","contents":"<p class=\"artist\">\n<a href=\"https://music.bugs.co.kr/artist/20058018?wl_ref=list_ab_04\" class=\"artistTitle\" title=\"lil thunder\" onclick=\"\n\" target=\"_self\">lil thunder</a>\n</p>\n<p>\n<time datetime=\"\">2023.05.09</time>\n<span class=\"albumType\">싱글</span>\n</p>","link":"https://music.bugs.co.kr/album/4086273?wl_ref=list_ab_03","retrieved":1683602311831,"image":"https://image.bugsm.co.kr/album/images/170/40862/4086273.jpg?version=20230510064043.0"},{"title":"너가 파티에선 주인공이지 (Feat. 하곤)","contents":"<p class=\"artist\">\n<!-- a tag title -->\n<a href=\"https://music.bugs.co.kr/artist/20047580?wl_ref=list_ab_04\" class=\"artistTitle\" title=\"림헤엄\">림헤엄</a>\n<!-- a tag link -->\n<a href=\"javascript:void(0);\" name=\"atag_martist_list\" class=\"more\" title=\"아티스트 전체보기\" wise_log_str=\"?wl_ref=list_ab_04\" onclick=\"bugs.layermenu.openMultiArtistSearchResultPopLayer(this, '림헤엄||림헤엄||20047580||OK\\\\nbemyfrnd||bemyfrnd||20082943||OK', ''); return false;\">\n림헤엄\n</a> </p>\n<p>\n<time datetime=\"\">2023.05.09</time>\n<span class=\"albumType\">싱글</span>\n</p>","link":"https://music.bugs.co.kr/album/31639587?wl_ref=list_ab_03","retrieved":1683602311832,"image":"https://image.bugsm.co.kr/album/images/170/316395/31639587.jpg?version=20230510152028.0"},{"title":"시작은 첫키스 OST Part.3","contents":"<p class=\"artist\">\n<a href=\"https://music.bugs.co.kr/artist/20131188?wl_ref=list_ab_04\" class=\"artistTitle\" title=\"21학번\" onclick=\"\n\" target=\"_self\">21학번</a>\n</p>\n<p>\n<time datetime=\"\">2023.05.08</time>\n<span class=\"albumType\">OST</span>\n</p>","link":"https://music.bugs.co.kr/album/4086171?wl_ref=list_ab_03","retrieved":1683537424327,"image":"https://image.bugsm.co.kr/album/images/170/40861/4086171.jpg?version=20230508180026.0"},{"title":"NO LIMIT","contents":"<p class=\"artist\">\n<a href=\"https://music.bugs.co.kr/artist/20102058?wl_ref=list_ab_04\" class=\"artistTitle\" title=\"CRAXY (크랙시)\" onclick=\"\n\" target=\"_self\">CRAXY (크랙시)</a>\n</p>\n<p>\n<time datetime=\"\">2023.05.09</time>\n<span class=\"albumType\">싱글</span>\n</p>","link":"https://music.bugs.co.kr/album/20564231?wl_ref=list_ab_03","retrieved":1683602311836,"image":"https://image.bugsm.co.kr/album/images/170/205642/20564231.jpg?version=20230509120022.0"},{"title":"똑바로 바라봐 (feat. 적재)","contents":"<p class=\"artist\">\n<a href=\"https://music.bugs.co.kr/artist/80253123?wl_ref=list_ab_04\" class=\"artistTitle\" title=\"Sunnie\" onclick=\"\n\" target=\"_self\">Sunnie</a>\n</p>\n<p>\n<time datetime=\"\">2023.05.09</time>\n<span class=\"albumType\">싱글</span>\n</p>","link":"https://music.bugs.co.kr/album/4086277?wl_ref=list_ab_03","retrieved":1683602311837,"image":"https://image.bugsm.co.kr/album/images/170/40862/4086277.jpg?version=20230510012455.0"},{"title":"3","contents":"<p class=\"artist\">\n<a href=\"https://music.bugs.co.kr/artist/20073876?wl_ref=list_ab_04\" class=\"artistTitle\" title=\"615\" onclick=\"\n\" target=\"_self\">615</a>\n</p>\n<p>\n<time datetime=\"\">2023.05.09</time>\n<span class=\"albumType\">EP(미니)</span>\n</p>","link":"https://music.bugs.co.kr/album/20563687?wl_ref=list_ab_03","retrieved":1683602311842,"image":"https://image.bugsm.co.kr/album/images/170/205636/20563687.jpg?version=20230509120022.0"},{"title":"Go Straight","contents":"<p class=\"artist\">\n<a href=\"https://music.bugs.co.kr/artist/20108521?wl_ref=list_ab_04\" class=\"artistTitle\" title=\"유로겸\" onclick=\"\n\" target=\"_self\">유로겸</a>\n</p>\n<p>\n<time datetime=\"\">2023.05.09</time>\n<span class=\"albumType\">싱글</span>\n</p>","link":"https://music.bugs.co.kr/album/20562551?wl_ref=list_ab_03","retrieved":1683602311843,"image":"https://image.bugsm.co.kr/album/images/170/205625/20562551.jpg?version=20230509120022.0"},{"title":"Heart Balloon","contents":"<p class=\"artist\">\n<a href=\"https://music.bugs.co.kr/artist/20158932?wl_ref=list_ab_04\" class=\"artistTitle\" title=\"이학주\" onclick=\"\n\" target=\"_self\">이학주</a>\n</p>\n<p>\n<time datetime=\"\">2023.05.09</time>\n<span class=\"albumType\">싱글</span>\n</p>","link":"https://music.bugs.co.kr/album/20563675?wl_ref=list_ab_03","retrieved":1683602311856,"image":"https://image.bugsm.co.kr/album/images/170/205636/20563675.jpg?version=20230510025143.0"},{"title":"RocK N RoLL","contents":"<p class=\"artist\">\n<a href=\"https://music.bugs.co.kr/artist/80272226?wl_ref=list_ab_04\" class=\"artistTitle\" title=\"매미(MEMI)\" onclick=\"\n\" target=\"_self\">매미(MEMI)</a>\n</p>\n<p>\n<time datetime=\"\">2023.05.09</time>\n<span class=\"albumType\">싱글</span>\n</p>","link":"https://music.bugs.co.kr/album/20564176?wl_ref=list_ab_03","retrieved":1683602311869,"image":"https://image.bugsm.co.kr/album/images/170/205641/20564176.jpg?version=20230510014016.0"},{"title":"카페 앵커리지 OST Part.14","contents":"<p class=\"artist\">\n<a href=\"https://music.bugs.co.kr/artist/20004618?wl_ref=list_ab_04\" class=\"artistTitle\" title=\"하진우\" onclick=\"\n\" target=\"_self\">하진우</a>\n</p>\n<p>\n<time datetime=\"\">2023.05.09</time>\n<span class=\"albumType\">OST</span>\n</p>","link":"https://music.bugs.co.kr/album/20564591?wl_ref=list_ab_03","retrieved":1683602311869,"image":"https://image.bugsm.co.kr/album/images/170/205645/20564591.jpg?version=20230509120022.0"},{"title":"Come Love","contents":"<p class=\"artist\">\n<a href=\"https://music.bugs.co.kr/artist/80115548?wl_ref=list_ab_04\" class=\"artistTitle\" title=\"김주환\" onclick=\"\n\" target=\"_self\">김주환</a>\n</p>\n<p>\n<time datetime=\"\">2023.05.09</time>\n<span class=\"albumType\">싱글</span>\n</p>","link":"https://music.bugs.co.kr/album/20564318?wl_ref=list_ab_03","retrieved":1683602311871,"image":"https://image.bugsm.co.kr/album/images/170/205643/20564318.jpg?version=20230509120022.0"},{"title":"츄르","contents":"<p class=\"artist\">\n<a href=\"https://music.bugs.co.kr/artist/20081763?wl_ref=list_ab_04\" class=\"artistTitle\" title=\"루크 (Luke)\" onclick=\"\n\" target=\"_self\">루크 (Luke)</a>\n</p>\n<p>\n<time datetime=\"\">2023.05.09</time>\n<span class=\"albumType\">싱글</span>\n</p>","link":"https://music.bugs.co.kr/album/20564338?wl_ref=list_ab_03","retrieved":1683602311872,"image":"https://image.bugsm.co.kr/album/images/170/205643/20564338.jpg?version=20230509120022.0"},{"title":"HERO.","contents":"<p class=\"artist\">\n<a href=\"https://music.bugs.co.kr/artist/20115772?wl_ref=list_ab_04\" class=\"artistTitle\" title=\"ROSESIA\" onclick=\"\n\" target=\"_self\">ROSESIA</a>\n</p>\n<p>\n<time datetime=\"\">2023.05.09</time>\n<span class=\"albumType\">싱글</span>\n</p>","link":"https://music.bugs.co.kr/album/20564235?wl_ref=list_ab_03","retrieved":1683602311874,"image":"https://image.bugsm.co.kr/album/images/170/205642/20564235.jpg?version=20230509120022.0"},{"title":"철수와 영희","contents":"<p class=\"artist\">\n<!-- a tag title -->\n<a href=\"https://music.bugs.co.kr/artist/20072780?wl_ref=list_ab_04\" class=\"artistTitle\" title=\"진혜진\">진혜진</a>\n<!-- a tag link -->\n<a href=\"javascript:void(0);\" name=\"atag_martist_list\" class=\"more\" title=\"아티스트 전체보기\" wise_log_str=\"?wl_ref=list_ab_04\" onclick=\"bugs.layermenu.openMultiArtistSearchResultPopLayer(this, '진혜진||진혜진||20072780||OK\\\\n장군||장군||20170826||OK', ''); return false;\">\n진혜진\n</a> </p>\n<p>\n<time datetime=\"\">2023.05.09</time>\n<span class=\"albumType\">싱글</span>\n</p>","link":"https://music.bugs.co.kr/album/20564389?wl_ref=list_ab_03","retrieved":1683602311903,"image":"https://image.bugsm.co.kr/album/images/170/205643/20564389.jpg?version=20230510013257.0"},{"title":"Don't worry","contents":"<p class=\"artist\">\n<a href=\"https://music.bugs.co.kr/artist/20121915?wl_ref=list_ab_04\" class=\"artistTitle\" title=\"Lil jibo\" onclick=\"\n\" target=\"_self\">Lil jibo</a>\n</p>\n<p>\n<time datetime=\"\">2023.05.09</time>\n<span class=\"albumType\">싱글</span>\n</p>","link":"https://music.bugs.co.kr/album/20564409?wl_ref=list_ab_03","retrieved":1683623799246,"image":"https://image.bugsm.co.kr/album/images/170/205644/20564409.jpg?version=20230510003028.0"},{"title":"Misty","contents":"<p class=\"artist\">\n<a href=\"https://music.bugs.co.kr/artist/80359551?wl_ref=list_ab_04\" class=\"artistTitle\" title=\"Kozy\" onclick=\"\n\" target=\"_self\">Kozy</a>\n</p>\n<p>\n<time datetime=\"\">2023.05.09</time>\n<span class=\"albumType\">정규</span>\n</p>","link":"https://music.bugs.co.kr/album/4086268?wl_ref=list_ab_03","retrieved":1683602311904,"image":"https://image.bugsm.co.kr/album/images/170/40862/4086268.jpg?version=20230510023530.0"},{"title":"몽중몽","contents":"<p class=\"artist\">\n<a href=\"https://music.bugs.co.kr/artist/80186080?wl_ref=list_ab_04\" class=\"artistTitle\" title=\"융단\" onclick=\"\n\" target=\"_self\">융단</a>\n</p>\n<p>\n<time datetime=\"\">2023.05.09</time>\n<span class=\"albumType\">싱글</span>\n</p>","link":"https://music.bugs.co.kr/album/20563694?wl_ref=list_ab_03","retrieved":1683602311905,"image":"https://image.bugsm.co.kr/album/images/170/205636/20563694.jpg?version=20230509120022.0"},{"title":"푸름","contents":"<p class=\"artist\">\n<!-- a tag title -->\n<a href=\"https://music.bugs.co.kr/artist/80196338?wl_ref=list_ab_04\" class=\"artistTitle\" title=\"그네\">그네</a>\n<!-- a tag link -->\n<a href=\"javascript:void(0);\" name=\"atag_martist_list\" class=\"more\" title=\"아티스트 전체보기\" wise_log_str=\"?wl_ref=list_ab_04\" onclick=\"bugs.layermenu.openMultiArtistSearchResultPopLayer(this, '그네||그네||80196338||OK\\\\n이서한||이서한||20093640||OK', ''); return false;\">\n그네\n</a> </p>\n<p>\n<time datetime=\"\">2023.05.09</time>\n<span class=\"albumType\">싱글</span>\n</p>","link":"https://music.bugs.co.kr/album/20564402?wl_ref=list_ab_03","retrieved":1683602311905,"image":"https://image.bugsm.co.kr/album/images/170/205644/20564402.jpg?version=20230509120022.0"},{"title":"Red Bicycle (빨간 자전거 타는 우체부)","contents":"<p class=\"artist\">\n<a href=\"https://music.bugs.co.kr/artist/20146719?wl_ref=list_ab_04\" class=\"artistTitle\" title=\"Saree McIntosh\" onclick=\"\n\" target=\"_self\">Saree McIntosh</a>\n</p>\n<p>\n<time datetime=\"\">2023.05.09</time>\n<span class=\"albumType\">싱글</span>\n</p>","link":"https://music.bugs.co.kr/album/20564094?wl_ref=list_ab_03","retrieved":1683602311906,"image":"https://image.bugsm.co.kr/album/images/170/205640/20564094.jpg?version=20230510003240.0"},{"title":"사표를 던지다","contents":"<p class=\"artist\">\n<a href=\"https://music.bugs.co.kr/artist/8066508?wl_ref=list_ab_04\" class=\"artistTitle\" title=\"강우경\" onclick=\"\n\" target=\"_self\">강우경</a>\n</p>\n<p>\n<time datetime=\"\">2023.05.09</time>\n<span class=\"albumType\">싱글</span>\n</p>","link":"https://music.bugs.co.kr/album/20564506?wl_ref=list_ab_03","retrieved":1683602311909,"image":"https://image.bugsm.co.kr/album/images/170/205645/20564506.jpg?version=20230509120022.0"}]}