{"title":"벅스 ─ 최신 음악 ─ 앨범 ─ 대한민국","url":"https://music.bugs.co.kr/newest/album/totalpicked?nation=KOR","favicon":"https://file.bugsm.co.kr/wbugs/common/faviconBugs.ico","elements":[{"title":"즐거운 크리스마스 겨울 인기동요","contents":"<p class=\"artist\">\n<a href=\"https://music.bugs.co.kr/artist/20050497?wl_ref=list_ab_04\" class=\"artistTitle\" title=\"뮤직키즈\" onclick=\"\n\" target=\"_self\">뮤직키즈</a>\n</p>\n<p>\n<time datetime=\"\">2024.11.25</time>\n<span class=\"albumType\">정규</span>\n</p>","link":"https://music.bugs.co.kr/album/20687153?wl_ref=list_ab_03","retrieved":1732508822656,"image":"https://image.bugsm.co.kr/album/images/170/206871/20687153.jpg?version=1732553912000"},{"title":"FLOW","contents":"<p class=\"artist\">\n<a href=\"https://music.bugs.co.kr/artist/20199318?wl_ref=list_ab_04\" class=\"artistTitle\" title=\"홍유진\" onclick=\"\n\" target=\"_self\">홍유진</a>\n</p>\n<p>\n<time datetime=\"\">2024.11.25</time>\n<span class=\"albumType\">정규</span>\n</p>","link":"https://music.bugs.co.kr/album/20687146?wl_ref=list_ab_03","retrieved":1732508822659,"image":"https://image.bugsm.co.kr/album/images/170/206871/20687146.jpg?version=1732503632000"},{"title":"달님이의 노래 1 (Chinese ver.)","contents":"<p class=\"artist\">\n<a href=\"https://music.bugs.co.kr/artist/20154819?wl_ref=list_ab_04\" class=\"artistTitle\" title=\"달님이\" onclick=\"\n\" target=\"_self\">달님이</a>\n</p>\n<p>\n<time datetime=\"\">2024.11.25</time>\n<span class=\"albumType\">정규</span>\n</p>","link":"https://music.bugs.co.kr/album/20687119?wl_ref=list_ab_03","retrieved":1732508822660,"image":"https://image.bugsm.co.kr/album/images/170/206871/20687119.jpg?version=1732503632000"},{"title":"Special Vol.3","contents":"<p class=\"artist\">\n<a href=\"https://music.bugs.co.kr/artist/20216368?wl_ref=list_ab_04\" class=\"artistTitle\" title=\"Pretty BG\" onclick=\"\n\" target=\"_self\">Pretty BG</a>\n</p>\n<p>\n<time datetime=\"\">2024.11.25</time>\n<span class=\"albumType\">정규</span>\n</p>","link":"https://music.bugs.co.kr/album/20686934?wl_ref=list_ab_03","retrieved":1732508822663,"image":"https://image.bugsm.co.kr/album/images/170/206869/20686934.jpg?version=1732503632000"},{"title":"Ode Of Loss","contents":"<p class=\"artist\">\n<a href=\"https://music.bugs.co.kr/artist/20206307?wl_ref=list_ab_04\" class=\"artistTitle\" title=\"Graily\" onclick=\"\n\" target=\"_self\">Graily</a>\n</p>\n<p>\n<time datetime=\"\">2024.11.25</time>\n<span class=\"albumType\">정규</span>\n</p>","link":"https://music.bugs.co.kr/album/20686924?wl_ref=list_ab_03","retrieved":1732508822664,"image":"https://image.bugsm.co.kr/album/images/170/206869/20686924.jpg?version=1732551581000"},{"title":"잠이 오지 않는 밤, 네 생각이 나서 그래","contents":"<p class=\"artist\">\n<!-- a tag title -->\n<a href=\"https://music.bugs.co.kr/artist/20223838?wl_ref=list_ab_04\" class=\"artistTitle\" title=\"Comfort yourself\">Comfort yourself</a>\n<!-- a tag link -->\n<a href=\"javascript:void(0);\" name=\"atag_martist_list\" class=\"more\" title=\"아티스트 전체보기\" wise_log_str=\"?wl_ref=list_ab_04\" onclick=\"bugs.layermenu.openMultiArtistSearchResultPopLayer(this, 'Comfort yourself||Comfort yourself||20223838||OK\\\\n정시형||정시형||20223839||OK', ''); return false;\">\nComfort yourself\n</a> </p>\n<p>\n<time datetime=\"\">2024.11.25</time>\n<span class=\"albumType\">정규</span>\n</p>","link":"https://music.bugs.co.kr/album/20686864?wl_ref=list_ab_03","retrieved":1732508822666,"image":"https://image.bugsm.co.kr/album/images/170/206868/20686864.jpg?version=1732503632000"},{"title":"난에임밴드 프로젝트","contents":"<p class=\"artist\">\n<!-- a tag title -->\n<a href=\"https://music.bugs.co.kr/artist/8064571?wl_ref=list_ab_04\" class=\"artistTitle\" title=\"김영곤\">김영곤</a>\n<!-- a tag link -->\n<a href=\"javascript:void(0);\" name=\"atag_martist_list\" class=\"more\" title=\"아티스트 전체보기\" wise_log_str=\"?wl_ref=list_ab_04\" onclick=\"bugs.layermenu.openMultiArtistSearchResultPopLayer(this, '김영곤||김영곤||8064571||OK\\\\n난에임밴드||난에임밴드||20223790||OK', ''); return false;\">\n김영곤\n</a> </p>\n<p>\n<time datetime=\"\">2024.11.25</time>\n<span class=\"albumType\">정규</span>\n</p>","link":"https://music.bugs.co.kr/album/20686735?wl_ref=list_ab_03","retrieved":1732508822666,"image":"https://image.bugsm.co.kr/album/images/170/206867/20686735.jpg?version=1732503632000"},{"title":"Beautiful Evening","contents":"<p class=\"artist\">\n<a href=\"https://music.bugs.co.kr/artist/13937819?wl_ref=list_ab_04\" class=\"artistTitle\" title=\"박연우\" onclick=\"\n\" target=\"_self\">박연우</a>\n</p>\n<p>\n<time datetime=\"\">2024.11.25</time>\n<span class=\"albumType\">정규</span>\n</p>","link":"https://music.bugs.co.kr/album/20686674?wl_ref=list_ab_03","retrieved":1732508822669,"image":"https://image.bugsm.co.kr/album/images/170/206866/20686674.jpg?version=1732503632000"},{"title":"Lofi Retreat","contents":"<p class=\"artist\">\n<a href=\"https://music.bugs.co.kr/artist/20175217?wl_ref=list_ab_04\" class=\"artistTitle\" title=\"무브 (MOOB)\" onclick=\"\n\" target=\"_self\">무브 (MOOB)</a>\n</p>\n<p>\n<time datetime=\"\">2024.11.25</time>\n<span class=\"albumType\">정규</span>\n</p>","link":"https://music.bugs.co.kr/album/20686568?wl_ref=list_ab_03","retrieved":1732508822671,"image":"https://image.bugsm.co.kr/album/images/170/206865/20686568.jpg?version=1732503632000"},{"title":"Lofi Rest Area","contents":"<p class=\"artist\">\n<a href=\"https://music.bugs.co.kr/artist/20175217?wl_ref=list_ab_04\" class=\"artistTitle\" title=\"무브 (MOOB)\" onclick=\"\n\" target=\"_self\">무브 (MOOB)</a>\n</p>\n<p>\n<time datetime=\"\">2024.11.25</time>\n<span class=\"albumType\">정규</span>\n</p>","link":"https://music.bugs.co.kr/album/20686566?wl_ref=list_ab_03","retrieved":1732508822674,"image":"https://image.bugsm.co.kr/album/images/170/206865/20686566.jpg?version=1732503632000"},{"title":"내가 하고 싶은 이야기","contents":"<p class=\"artist\">\n<a href=\"https://music.bugs.co.kr/artist/20206685?wl_ref=list_ab_04\" class=\"artistTitle\" title=\"소박한 사람들\" onclick=\"\n\" target=\"_self\">소박한 사람들</a>\n</p>\n<p>\n<time datetime=\"\">2024.11.25</time>\n<span class=\"albumType\">정규</span>\n</p>","link":"https://music.bugs.co.kr/album/20686522?wl_ref=list_ab_03","retrieved":1732508822676,"image":"https://image.bugsm.co.kr/album/images/170/206865/20686522.jpg?version=1732503632000"},{"title":"험티밴드와 함께 노래해요","contents":"<p class=\"artist\">\n<a href=\"https://music.bugs.co.kr/artist/80245636?wl_ref=list_ab_04\" class=\"artistTitle\" title=\"험티밴드\" onclick=\"\n\" target=\"_self\">험티밴드</a>\n</p>\n<p>\n<time datetime=\"\">2024.11.25</time>\n<span class=\"albumType\">정규</span>\n</p>","link":"https://music.bugs.co.kr/album/20686497?wl_ref=list_ab_03","retrieved":1732508822676,"image":"https://image.bugsm.co.kr/album/images/170/206864/20686497.jpg?version=1732503632000"},{"title":"숙면을 위한 재즈","contents":"<p class=\"artist\">\n<a href=\"https://music.bugs.co.kr/artist/20214124?wl_ref=list_ab_04\" class=\"artistTitle\" title=\"LeoSky\" onclick=\"\n\" target=\"_self\">LeoSky</a>\n</p>\n<p>\n<time datetime=\"\">2024.11.25</time>\n<span class=\"albumType\">정규</span>\n</p>","link":"https://music.bugs.co.kr/album/20686396?wl_ref=list_ab_03","retrieved":1732508822677,"image":"https://image.bugsm.co.kr/album/images/170/206863/20686396.jpg?version=1732503632000"},{"title":"A World Filled With Lies","contents":"<p class=\"artist\">\n<a href=\"https://music.bugs.co.kr/artist/20116310?wl_ref=list_ab_04\" class=\"artistTitle\" title=\"TTRM (Titanrium)\" onclick=\"\n\" target=\"_self\">TTRM (Titanrium)</a>\n</p>\n<p>\n<time datetime=\"\">2024.11.25</time>\n<span class=\"albumType\">정규</span>\n</p>","link":"https://music.bugs.co.kr/album/20686170?wl_ref=list_ab_03","retrieved":1732508822678,"image":"https://image.bugsm.co.kr/album/images/170/206861/20686170.jpg?version=1732503632000"},{"title":"성령의 열매","contents":"<p class=\"artist\">\n<a href=\"https://music.bugs.co.kr/artist/20208735?wl_ref=list_ab_04\" class=\"artistTitle\" title=\"제이러브\" onclick=\"\n\" target=\"_self\">제이러브</a>\n</p>\n<p>\n<time datetime=\"\">2024.11.25</time>\n<span class=\"albumType\">정규</span>\n</p>","link":"https://music.bugs.co.kr/album/20685925?wl_ref=list_ab_03","retrieved":1732508822680,"image":"https://image.bugsm.co.kr/album/images/170/206859/20685925.jpg?version=1732559055000"},{"title":"Warm Rain","contents":"<p class=\"artist\">\n<a href=\"https://music.bugs.co.kr/artist/20222565?wl_ref=list_ab_04\" class=\"artistTitle\" title=\"Frosted Petals\" onclick=\"\n\" target=\"_self\">Frosted Petals</a>\n</p>\n<p>\n<time datetime=\"\">2024.11.25</time>\n<span class=\"albumType\">정규</span>\n</p>","link":"https://music.bugs.co.kr/album/20685668?wl_ref=list_ab_03","retrieved":1732508822682,"image":"https://image.bugsm.co.kr/album/images/170/206856/20685668.jpg?version=1732503632000"},{"title":"in Seoul, 1978","contents":"<p class=\"artist\">\n<a href=\"https://music.bugs.co.kr/artist/20178746?wl_ref=list_ab_04\" class=\"artistTitle\" title=\"그루비제이\" onclick=\"\n\" target=\"_self\">그루비제이</a>\n</p>\n<p>\n<time datetime=\"\">2024.11.25</time>\n<span class=\"albumType\">정규</span>\n</p>","link":"https://music.bugs.co.kr/album/20685573?wl_ref=list_ab_03","retrieved":1732508822682,"image":"https://image.bugsm.co.kr/album/images/170/206855/20685573.jpg?version=1732554553000"},{"title":"고향으로가는배","contents":"<p class=\"artist\">\n<a href=\"https://music.bugs.co.kr/artist/20223420?wl_ref=list_ab_04\" class=\"artistTitle\" title=\"김민진\" onclick=\"\n\" target=\"_self\">김민진</a>\n</p>\n<p>\n<time datetime=\"\">2024.11.25</time>\n<span class=\"albumType\">정규</span>\n</p>","link":"https://music.bugs.co.kr/album/20685439?wl_ref=list_ab_03","retrieved":1732508822683,"image":"https://image.bugsm.co.kr/album/images/170/206854/20685439.jpg?version=1732503632000"},{"title":"하랑의 4집 COVER 모음","contents":"<p class=\"artist\">\n<a href=\"https://music.bugs.co.kr/artist/20204760?wl_ref=list_ab_04\" class=\"artistTitle\" title=\"하랑\" onclick=\"\n\" target=\"_self\">하랑</a>\n</p>\n<p>\n<time datetime=\"\">2024.11.25</time>\n<span class=\"albumType\">정규</span>\n</p>","link":"https://music.bugs.co.kr/album/20685432?wl_ref=list_ab_03","retrieved":1732508822684,"image":"https://image.bugsm.co.kr/album/images/170/206854/20685432.jpg?version=1732503632000"},{"title":"대사냥의 2024 제8집 눈물난다","contents":"<p class=\"artist\">\n<a href=\"https://music.bugs.co.kr/artist/20216402?wl_ref=list_ab_04\" class=\"artistTitle\" title=\"대사냥\" onclick=\"\n\" target=\"_self\">대사냥</a>\n</p>\n<p>\n<time datetime=\"\">2024.11.25</time>\n<span class=\"albumType\">정규</span>\n</p>","link":"https://music.bugs.co.kr/album/20685426?wl_ref=list_ab_03","retrieved":1732508822685,"image":"https://image.bugsm.co.kr/album/images/170/206854/20685426.jpg?version=1732503632000"},{"title":"가요여행","contents":"<p class=\"artist\">\n<a href=\"https://music.bugs.co.kr/artist/20173527?wl_ref=list_ab_04\" class=\"artistTitle\" title=\"송현주\" onclick=\"\n\" target=\"_self\">송현주</a>\n</p>\n<p>\n<time datetime=\"\">2024.11.25</time>\n<span class=\"albumType\">정규</span>\n</p>","link":"https://music.bugs.co.kr/album/20685424?wl_ref=list_ab_03","retrieved":1732508822686,"image":"https://image.bugsm.co.kr/album/images/170/206854/20685424.jpg?version=1732503632000"},{"title":"glimpse category","contents":"<p class=\"artist\">\n<a href=\"https://music.bugs.co.kr/artist/20223410?wl_ref=list_ab_04\" class=\"artistTitle\" title=\"HBXA\" onclick=\"\n\" target=\"_self\">HBXA</a>\n</p>\n<p>\n<time datetime=\"\">2024.11.25</time>\n<span class=\"albumType\">정규</span>\n</p>","link":"https://music.bugs.co.kr/album/20685412?wl_ref=list_ab_03","retrieved":1732508822687,"image":"https://image.bugsm.co.kr/album/images/170/206854/20685412.jpg?version=1732503632000"},{"title":"Music for Ballet Class, vol.21 : 발레 클래스 음악","contents":"<p class=\"artist\">\n<a href=\"https://music.bugs.co.kr/artist/20079777?wl_ref=list_ab_04\" class=\"artistTitle\" title=\"김은수\" onclick=\"\n\" target=\"_self\">김은수</a>\n</p>\n<p>\n<time datetime=\"\">2024.11.25</time>\n<span class=\"albumType\">정규</span>\n</p>","link":"https://music.bugs.co.kr/album/20685407?wl_ref=list_ab_03","retrieved":1732508822688,"image":"https://image.bugsm.co.kr/album/images/170/206854/20685407.jpg?version=1732503632000"},{"title":"마음이 편해지는 명상 & 요가음악","contents":"<p class=\"artist\">\n<a href=\"https://music.bugs.co.kr/artist/20214606?wl_ref=list_ab_04\" class=\"artistTitle\" title=\"진블리\" onclick=\"\n\" target=\"_self\">진블리</a>\n</p>\n<p>\n<time datetime=\"\">2024.11.25</time>\n<span class=\"albumType\">정규</span>\n</p>","link":"https://music.bugs.co.kr/album/20685405?wl_ref=list_ab_03","retrieved":1732508822690,"image":"https://image.bugsm.co.kr/album/images/170/206854/20685405.jpg?version=1732503632000"},{"title":"제4회 인천교구 청년 1945 창작생활성가제","contents":"<p class=\"artist\">\n<span class=\"artistTitle\" title=\"\">Various Artists</span>\n</p>\n<p>\n<time datetime=\"\">2024.11.25</time>\n<span class=\"albumType\">정규</span>\n</p>","link":"https://music.bugs.co.kr/album/20685403?wl_ref=list_ab_03","retrieved":1732508822695,"image":"https://image.bugsm.co.kr/album/images/170/206854/20685403.jpg?version=1732503632000"},{"title":"같이 걸을까요","contents":"<p class=\"artist\">\n<a href=\"https://music.bugs.co.kr/artist/20223357?wl_ref=list_ab_04\" class=\"artistTitle\" title=\"폴 인 피아노\" onclick=\"\n\" target=\"_self\">폴 인 피아노</a>\n</p>\n<p>\n<time datetime=\"\">2024.11.25</time>\n<span class=\"albumType\">정규</span>\n</p>","link":"https://music.bugs.co.kr/album/20685284?wl_ref=list_ab_03","retrieved":1732508822697,"image":"https://image.bugsm.co.kr/album/images/170/206852/20685284.jpg?version=1732503632000"},{"title":"Traffic Jam","contents":"<p class=\"artist\">\n<a href=\"https://music.bugs.co.kr/artist/13865012?wl_ref=list_ab_04\" class=\"artistTitle\" title=\"quiet.b\" onclick=\"\n\" target=\"_self\">quiet.b</a>\n</p>\n<p>\n<time datetime=\"\">2024.11.25</time>\n<span class=\"albumType\">정규</span>\n</p>","link":"https://music.bugs.co.kr/album/4110743?wl_ref=list_ab_03","retrieved":1732530274143,"image":"https://image.bugsm.co.kr/album/images/170/41107/4110743.jpg?version=1732525234000"},{"title":"Glacial City","contents":"<p class=\"artist\">\n<a href=\"https://music.bugs.co.kr/artist/13983651?wl_ref=list_ab_04\" class=\"artistTitle\" title=\"Our Silence\" onclick=\"\n\" target=\"_self\">Our Silence</a>\n</p>\n<p>\n<time datetime=\"\">2024.11.25</time>\n<span class=\"albumType\">정규</span>\n</p>","link":"https://music.bugs.co.kr/album/4110742?wl_ref=list_ab_03","retrieved":1732530274145,"image":"https://image.bugsm.co.kr/album/images/170/41107/4110742.jpg?version=1732525234000"},{"title":"Winter In Paris","contents":"<p class=\"artist\">\n<a href=\"https://music.bugs.co.kr/artist/13807794?wl_ref=list_ab_04\" class=\"artistTitle\" title=\"SMOOTH LOUNGE\" onclick=\"\n\" target=\"_self\">SMOOTH LOUNGE</a>\n</p>\n<p>\n<time datetime=\"\">2024.11.25</time>\n<span class=\"albumType\">정규</span>\n</p>","link":"https://music.bugs.co.kr/album/4110741?wl_ref=list_ab_03","retrieved":1732508822700,"image":"https://image.bugsm.co.kr/album/images/170/41107/4110741.jpg?version=1732503632000"},{"title":"My King","contents":"<p class=\"artist\">\n<a href=\"https://music.bugs.co.kr/artist/80397739?wl_ref=list_ab_04\" class=\"artistTitle\" title=\"딜라이티\" onclick=\"\n\" target=\"_self\">딜라이티</a>\n</p>\n<p>\n<time datetime=\"\">2024.11.25</time>\n<span class=\"albumType\">정규</span>\n</p>","link":"https://music.bugs.co.kr/album/4110671?wl_ref=list_ab_03","retrieved":1732508822701,"image":"https://image.bugsm.co.kr/album/images/170/41106/4110671.jpg?version=1732503632000"},{"title":"IBK TOGETHER 2024","contents":"<p class=\"artist\">\n<!-- a tag title -->\n<a href=\"https://music.bugs.co.kr/artist/20072547?wl_ref=list_ab_04\" class=\"artistTitle\" title=\"대니 구(Danny Koo)\">대니 구(Danny Koo)</a>\n<!-- a tag link -->\n<a href=\"javascript:void(0);\" name=\"atag_martist_list\" class=\"more\" title=\"아티스트 전체보기\" wise_log_str=\"?wl_ref=list_ab_04\" onclick=\"bugs.layermenu.openMultiArtistSearchResultPopLayer(this, '대니 구||대니 구(Danny Koo)||20072547||OK\\\\n조윤성||조윤성||31742||OK\\\\n김보경||김보경||20160020||OK\\\\n이정현||이정현||20223901||OK\\\\n엄희준||엄희준||20223902||OK\\\\n황희섭||황희섭||20223903||OK', ''); return false;\">\n대니 구(Danny Koo)\n</a> </p>\n<p>\n<time datetime=\"\">2024.11.25</time>\n<span class=\"albumType\">EP(미니)</span>\n</p>","link":"https://music.bugs.co.kr/album/20687117?wl_ref=list_ab_03","retrieved":1732508822702,"image":"https://image.bugsm.co.kr/album/images/170/206871/20687117.jpg?version=1732503609000"},{"title":"나야 땡큐지","contents":"<p class=\"artist\">\n<a href=\"https://music.bugs.co.kr/artist/20054615?wl_ref=list_ab_04\" class=\"artistTitle\" title=\"황락천\" onclick=\"\n\" target=\"_self\">황락천</a>\n</p>\n<p>\n<time datetime=\"\">2024.11.25</time>\n<span class=\"albumType\">EP(미니)</span>\n</p>","link":"https://music.bugs.co.kr/album/20687029?wl_ref=list_ab_03","retrieved":1732508822708,"image":"https://image.bugsm.co.kr/album/images/170/206870/20687029.jpg?version=1732503632000"},{"title":"H's note","contents":"<p class=\"artist\">\n<a href=\"https://music.bugs.co.kr/artist/20223875?wl_ref=list_ab_04\" class=\"artistTitle\" title=\"H\" onclick=\"\n\" target=\"_self\">H</a>\n</p>\n<p>\n<time datetime=\"\">2024.11.25</time>\n<span class=\"albumType\">EP(미니)</span>\n</p>","link":"https://music.bugs.co.kr/album/20686994?wl_ref=list_ab_03","retrieved":1732508822709,"image":"https://image.bugsm.co.kr/album/images/170/206869/20686994.jpg?version=1732503632000"},{"title":"인과연","contents":"<p class=\"artist\">\n<a href=\"https://music.bugs.co.kr/artist/20218085?wl_ref=list_ab_04\" class=\"artistTitle\" title=\"류하늘\" onclick=\"\n\" target=\"_self\">류하늘</a>\n</p>\n<p>\n<time datetime=\"\">2024.11.25</time>\n<span class=\"albumType\">EP(미니)</span>\n</p>","link":"https://music.bugs.co.kr/album/20686862?wl_ref=list_ab_03","retrieved":1732508822709,"image":"https://image.bugsm.co.kr/album/images/170/206868/20686862.jpg?version=1732557665000"},{"title":"Sunset River Panorama","contents":"<p class=\"artist\">\n<a href=\"https://music.bugs.co.kr/artist/80216097?wl_ref=list_ab_04\" class=\"artistTitle\" title=\"밴드 12시\" onclick=\"\n\" target=\"_self\">밴드 12시</a>\n</p>\n<p>\n<time datetime=\"\">2024.11.25</time>\n<span class=\"albumType\">EP(미니)</span>\n</p>","link":"https://music.bugs.co.kr/album/20686861?wl_ref=list_ab_03","retrieved":1732508822712,"image":"https://image.bugsm.co.kr/album/images/170/206868/20686861.jpg?version=1732503632000"},{"title":"DAILY MOOD","contents":"<p class=\"artist\">\n<a href=\"https://music.bugs.co.kr/artist/20220139?wl_ref=list_ab_04\" class=\"artistTitle\" title=\"지꿍(JIKOON)\" onclick=\"\n\" target=\"_self\">지꿍(JIKOON)</a>\n</p>\n<p>\n<time datetime=\"\">2024.11.25</time>\n<span class=\"albumType\">EP(미니)</span>\n</p>","link":"https://music.bugs.co.kr/album/20686858?wl_ref=list_ab_03","retrieved":1732508822715,"image":"https://image.bugsm.co.kr/album/images/170/206868/20686858.jpg?version=1732503632000"},{"title":"Over the moon","contents":"<p class=\"artist\">\n<!-- a tag title -->\n<a href=\"https://music.bugs.co.kr/artist/20165694?wl_ref=list_ab_04\" class=\"artistTitle\" title=\"NOAH\">NOAH</a>\n<!-- a tag link -->\n<a href=\"javascript:void(0);\" name=\"atag_martist_list\" class=\"more\" title=\"아티스트 전체보기\" wise_log_str=\"?wl_ref=list_ab_04\" onclick=\"bugs.layermenu.openMultiArtistSearchResultPopLayer(this, 'NOAH||NOAH||20165694||OK\\\\nJINO||JINO||20171361||OK', ''); return false;\">\nNOAH\n</a> </p>\n<p>\n<time datetime=\"\">2024.11.25</time>\n<span class=\"albumType\">EP(미니)</span>\n</p>","link":"https://music.bugs.co.kr/album/20686848?wl_ref=list_ab_03","retrieved":1732530274160,"image":"https://image.bugsm.co.kr/album/images/170/206868/20686848.jpg?version=1732525234000"},{"title":"Soloist","contents":"<p class=\"artist\">\n<a href=\"https://music.bugs.co.kr/artist/20082077?wl_ref=list_ab_04\" class=\"artistTitle\" title=\"BIG YAWN\" onclick=\"\n\" target=\"_self\">BIG YAWN</a>\n</p>\n<p>\n<time datetime=\"\">2024.11.25</time>\n<span class=\"albumType\">EP(미니)</span>\n</p>","link":"https://music.bugs.co.kr/album/20686844?wl_ref=list_ab_03","retrieved":1732508822715,"image":"https://image.bugsm.co.kr/album/images/170/206868/20686844.jpg?version=1732550284000"},{"title":"Bloody Emotion","contents":"<p class=\"artist\">\n<a href=\"https://music.bugs.co.kr/artist/20144919?wl_ref=list_ab_04\" class=\"artistTitle\" title=\"Ashall\" onclick=\"\n\" target=\"_self\">Ashall</a>\n</p>\n<p>\n<time datetime=\"\">2024.11.25</time>\n<span class=\"albumType\">EP(미니)</span>\n</p>","link":"https://music.bugs.co.kr/album/20686833?wl_ref=list_ab_03","retrieved":1732530274166,"image":"https://image.bugsm.co.kr/album/images/170/206868/20686833.jpg?version=1732552842000"},{"title":"Signs","contents":"<p class=\"artist\">\n<!-- a tag title -->\n<a href=\"https://music.bugs.co.kr/artist/80013053?wl_ref=list_ab_04\" class=\"artistTitle\" title=\"이노경(Nokyung Lee)\">이노경(Nokyung Lee)</a>\n<!-- a tag link -->\n<a href=\"javascript:void(0);\" name=\"atag_martist_list\" class=\"more\" title=\"아티스트 전체보기\" wise_log_str=\"?wl_ref=list_ab_04\" onclick=\"bugs.layermenu.openMultiArtistSearchResultPopLayer(this, '이노경||이노경(Nokyung Lee)||80013053||OK\\\\n정재민||정재민||20223722||OK', ''); return false;\">\n이노경(Nokyung Lee)\n</a> </p>\n<p>\n<time datetime=\"\">2024.11.25</time>\n<span class=\"albumType\">EP(미니)</span>\n</p>","link":"https://music.bugs.co.kr/album/20686531?wl_ref=list_ab_03","retrieved":1732508822715,"image":"https://image.bugsm.co.kr/album/images/170/206865/20686531.jpg?version=1732503632000"},{"title":"Cadence (Sped Up)","contents":"<p class=\"artist\">\n<a href=\"https://music.bugs.co.kr/artist/20129734?wl_ref=list_ab_04\" class=\"artistTitle\" title=\"SLOWPIPE\" onclick=\"\n\" target=\"_self\">SLOWPIPE</a>\n</p>\n<p>\n<time datetime=\"\">2024.11.25</time>\n<span class=\"albumType\">EP(미니)</span>\n</p>","link":"https://music.bugs.co.kr/album/20686508?wl_ref=list_ab_03","retrieved":1732530274167,"image":"https://image.bugsm.co.kr/album/images/170/206865/20686508.jpg?version=1732552846000"},{"title":"태화연가(太和戀歌)","contents":"<p class=\"artist\">\n<a href=\"https://music.bugs.co.kr/artist/20102768?wl_ref=list_ab_04\" class=\"artistTitle\" title=\"Odd95\" onclick=\"\n\" target=\"_self\">Odd95</a>\n</p>\n<p>\n<time datetime=\"\">2024.11.25</time>\n<span class=\"albumType\">EP(미니)</span>\n</p>","link":"https://music.bugs.co.kr/album/20686414?wl_ref=list_ab_03","retrieved":1732530274169,"image":"https://image.bugsm.co.kr/album/images/170/206864/20686414.jpg?version=1732525228000"},{"title":"N/a","contents":"<p class=\"artist\">\n<a href=\"https://music.bugs.co.kr/artist/80401603?wl_ref=list_ab_04\" class=\"artistTitle\" title=\"izna (이즈나)\" onclick=\"\n\" target=\"_self\">izna (이즈나)</a>\n</p>\n<p>\n<time datetime=\"\">2024.11.25</time>\n<span class=\"albumType\">EP(미니)</span>\n</p>","link":"https://music.bugs.co.kr/album/20686303?wl_ref=list_ab_03","retrieved":1732530274170,"image":"https://image.bugsm.co.kr/album/images/170/206863/20686303.jpg?version=1732552492000"},{"title":"도와주세요","contents":"<p class=\"artist\">\n<a href=\"https://music.bugs.co.kr/artist/20210617?wl_ref=list_ab_04\" class=\"artistTitle\" title=\"재우\" onclick=\"\n\" target=\"_self\">재우</a>\n</p>\n<p>\n<time datetime=\"\">2024.11.25</time>\n<span class=\"albumType\">EP(미니)</span>\n</p>","link":"https://music.bugs.co.kr/album/20686282?wl_ref=list_ab_03","retrieved":1732508822717,"image":"https://image.bugsm.co.kr/album/images/170/206862/20686282.jpg?version=1732552842000"},{"title":"dreamscape","contents":"<p class=\"artist\">\n<a href=\"https://music.bugs.co.kr/artist/20194778?wl_ref=list_ab_04\" class=\"artistTitle\" title=\"LBH\" onclick=\"\n\" target=\"_self\">LBH</a>\n</p>\n<p>\n<time datetime=\"\">2024.11.25</time>\n<span class=\"albumType\">EP(미니)</span>\n</p>","link":"https://music.bugs.co.kr/album/20686132?wl_ref=list_ab_03","retrieved":1732508822717,"image":"https://image.bugsm.co.kr/album/images/170/206861/20686132.jpg?version=1732503632000"},{"title":"Alarm","contents":"<p class=\"artist\">\n<a href=\"https://music.bugs.co.kr/artist/80109088?wl_ref=list_ab_04\" class=\"artistTitle\" title=\"투스테이(2Stay)\" onclick=\"\n\" target=\"_self\">투스테이(2Stay)</a>\n</p>\n<p>\n<time datetime=\"\">2024.11.25</time>\n<span class=\"albumType\">EP(미니)</span>\n</p>","link":"https://music.bugs.co.kr/album/20686130?wl_ref=list_ab_03","retrieved":1732508822719,"image":"https://image.bugsm.co.kr/album/images/170/206861/20686130.jpg?version=1732503632000"},{"title":"Kamyu's Waltz","contents":"<p class=\"artist\">\n<a href=\"https://music.bugs.co.kr/artist/20194646?wl_ref=list_ab_04\" class=\"artistTitle\" title=\"작곡하는 경영학도\" onclick=\"\n\" target=\"_self\">작곡하는 경영학도</a>\n</p>\n<p>\n<time datetime=\"\">2024.11.25</time>\n<span class=\"albumType\">EP(미니)</span>\n</p>","link":"https://music.bugs.co.kr/album/20686126?wl_ref=list_ab_03","retrieved":1732508822720,"image":"https://image.bugsm.co.kr/album/images/170/206861/20686126.jpg?version=1732503632000"},{"title":"Start Over","contents":"<p class=\"artist\">\n<a href=\"https://music.bugs.co.kr/artist/20157208?wl_ref=list_ab_04\" class=\"artistTitle\" title=\"Kaneya\" onclick=\"\n\" target=\"_self\">Kaneya</a>\n</p>\n<p>\n<time datetime=\"\">2024.11.25</time>\n<span class=\"albumType\">EP(미니)</span>\n</p>","link":"https://music.bugs.co.kr/album/20686109?wl_ref=list_ab_03","retrieved":1732508822722,"image":"https://image.bugsm.co.kr/album/images/170/206861/20686109.jpg?version=1732503632000"},{"title":"Dear","contents":"<p class=\"artist\">\n<a href=\"https://music.bugs.co.kr/artist/20122703?wl_ref=list_ab_04\" class=\"artistTitle\" title=\"Chaserose(체이서로즈)\" onclick=\"\n\" target=\"_self\">Chaserose(체이서로즈)</a>\n</p>\n<p>\n<time datetime=\"\">2024.11.25</time>\n<span class=\"albumType\">EP(미니)</span>\n</p>","link":"https://music.bugs.co.kr/album/4110744?wl_ref=list_ab_03","retrieved":1732530274196,"image":"https://image.bugsm.co.kr/album/images/170/41107/4110744.jpg?version=1732525234000"},{"title":"FREQUENCY - The 6th Mini Album","contents":"<p class=\"artist\">\n<a href=\"https://music.bugs.co.kr/artist/80325652?wl_ref=list_ab_04\" class=\"artistTitle\" title=\"WayV\" onclick=\"\n\" target=\"_self\">WayV</a>\n</p>\n<p>\n<time datetime=\"\">2024.11.25</time>\n<span class=\"albumType\">EP(미니)</span>\n</p>","link":"https://music.bugs.co.kr/album/4109933?wl_ref=list_ab_03","retrieved":1732508822724,"image":"https://image.bugsm.co.kr/album/images/170/41099/4109933.jpg?version=1732558354000"},{"title":"행복하고 싶어","contents":"<p class=\"artist\">\n<a href=\"https://music.bugs.co.kr/artist/13984450?wl_ref=list_ab_04\" class=\"artistTitle\" title=\"자정\" onclick=\"\n\" target=\"_self\">자정</a>\n</p>\n<p>\n<time datetime=\"\">2024.11.25</time>\n<span class=\"albumType\">싱글</span>\n</p>","link":"https://music.bugs.co.kr/album/36430033?wl_ref=list_ab_03","retrieved":1732508822725,"image":"https://image.bugsm.co.kr/album/images/170/364300/36430033.jpg?version=1732503621000"},{"title":"We will sail for your freedom","contents":"<p class=\"artist\">\n<a href=\"https://music.bugs.co.kr/artist/13961066?wl_ref=list_ab_04\" class=\"artistTitle\" title=\"모레도토요일\" onclick=\"\n\" target=\"_self\">모레도토요일</a>\n</p>\n<p>\n<time datetime=\"\">2024.11.25</time>\n<span class=\"albumType\">싱글</span>\n</p>","link":"https://music.bugs.co.kr/album/36322823?wl_ref=list_ab_03","retrieved":1732508822727,"image":"https://image.bugsm.co.kr/album/images/170/363228/36322823.jpg?version=1732548596000"},{"title":"2024 월간 윤종신 11월호","contents":"<p class=\"artist\">\n<a href=\"https://music.bugs.co.kr/artist/2459?wl_ref=list_ab_04\" class=\"artistTitle\" title=\"윤종신\" onclick=\"\n\" target=\"_self\">윤종신</a>\n</p>\n<p>\n<time datetime=\"\">2024.11.25</time>\n<span class=\"albumType\">싱글</span>\n</p>","link":"https://music.bugs.co.kr/album/20687352?wl_ref=list_ab_03","retrieved":1732530274201,"image":"https://image.bugsm.co.kr/album/images/170/206873/20687352.jpg?version=1732559056000"},{"title":"비로소 너를 깨달았다","contents":"<p class=\"artist\">\n<a href=\"https://music.bugs.co.kr/artist/20104304?wl_ref=list_ab_04\" class=\"artistTitle\" title=\"ONSEEON (온시온)\" onclick=\"\n\" target=\"_self\">ONSEEON (온시온)</a>\n</p>\n<p>\n<time datetime=\"\">2024.11.25</time>\n<span class=\"albumType\">싱글</span>\n</p>","link":"https://music.bugs.co.kr/album/20687346?wl_ref=list_ab_03","retrieved":1732530274203,"image":"https://image.bugsm.co.kr/album/images/170/206873/20687346.jpg?version=1732556446000"},{"title":"[Chapter M Project] 6th Chapter '사랑이니까, 유일한 내 빛이니까'","contents":"<p class=\"artist\">\n<a href=\"https://music.bugs.co.kr/artist/80204221?wl_ref=list_ab_04\" class=\"artistTitle\" title=\"이라온\" onclick=\"\n\" target=\"_self\">이라온</a>\n</p>\n<p>\n<time datetime=\"\">2024.11.25</time>\n<span class=\"albumType\">싱글</span>\n</p>","link":"https://music.bugs.co.kr/album/20687341?wl_ref=list_ab_03","retrieved":1732508822729,"image":"https://image.bugsm.co.kr/album/images/170/206873/20687341.jpg?version=1732553372000"},{"title":"행복해요","contents":"<p class=\"artist\">\n<a href=\"https://music.bugs.co.kr/artist/20190749?wl_ref=list_ab_04\" class=\"artistTitle\" title=\"한수민\" onclick=\"\n\" target=\"_self\">한수민</a>\n</p>\n<p>\n<time datetime=\"\">2024.11.25</time>\n<span class=\"albumType\">싱글</span>\n</p>","link":"https://music.bugs.co.kr/album/20687325?wl_ref=list_ab_03","retrieved":1732508822731,"image":"https://image.bugsm.co.kr/album/images/170/206873/20687325.jpg?version=1732550230000"},{"title":"너와 함께 할꺼야","contents":"<p class=\"artist\">\n<a href=\"https://music.bugs.co.kr/artist/20223951?wl_ref=list_ab_04\" class=\"artistTitle\" title=\"Skywon (스카이원)\" onclick=\"\n\" target=\"_self\">Skywon (스카이원)</a>\n</p>\n<p>\n<time datetime=\"\">2024.11.25</time>\n<span class=\"albumType\">싱글</span>\n</p>","link":"https://music.bugs.co.kr/album/20687291?wl_ref=list_ab_03","retrieved":1732508822732,"image":"https://image.bugsm.co.kr/album/images/170/206872/20687291.jpg?version=1732550977000"},{"title":"Run Out","contents":"<p class=\"artist\">\n<a href=\"https://music.bugs.co.kr/artist/20068604?wl_ref=list_ab_04\" class=\"artistTitle\" title=\"CIDO (씨도)\" onclick=\"\n\" target=\"_self\">CIDO (씨도)</a>\n</p>\n<p>\n<time datetime=\"\">2024.11.25</time>\n<span class=\"albumType\">싱글</span>\n</p>","link":"https://music.bugs.co.kr/album/20687197?wl_ref=list_ab_03","retrieved":1732508822734,"image":"https://image.bugsm.co.kr/album/images/170/206871/20687197.jpg?version=1732503632000"},{"title":"It's time","contents":"<p class=\"artist\">\n<a href=\"https://music.bugs.co.kr/artist/20194194?wl_ref=list_ab_04\" class=\"artistTitle\" title=\"JooS\" onclick=\"\n\" target=\"_self\">JooS</a>\n</p>\n<p>\n<time datetime=\"\">2024.11.25</time>\n<span class=\"albumType\">싱글</span>\n</p>","link":"https://music.bugs.co.kr/album/20687189?wl_ref=list_ab_03","retrieved":1732508822735,"image":"https://image.bugsm.co.kr/album/images/170/206871/20687189.jpg?version=1732503612000"},{"title":"Moonstone","contents":"<p class=\"artist\">\n<!-- a tag title -->\n<a href=\"https://music.bugs.co.kr/artist/20223921?wl_ref=list_ab_04\" class=\"artistTitle\" title=\"문영원\">문영원</a>\n<!-- a tag link -->\n<a href=\"javascript:void(0);\" name=\"atag_martist_list\" class=\"more\" title=\"아티스트 전체보기\" wise_log_str=\"?wl_ref=list_ab_04\" onclick=\"bugs.layermenu.openMultiArtistSearchResultPopLayer(this, '문영원||문영원||20223921||OK\\\\n이성현||이성현||80397249||OK', ''); return false;\">\n문영원\n</a> </p>\n<p>\n<time datetime=\"\">2024.11.25</time>\n<span class=\"albumType\">싱글</span>\n</p>","link":"https://music.bugs.co.kr/album/20687187?wl_ref=list_ab_03","retrieved":1732508822737,"image":"https://image.bugsm.co.kr/album/images/170/206871/20687187.jpg?version=1732554634000"},{"title":"편지","contents":"<p class=\"artist\">\n<a href=\"https://music.bugs.co.kr/artist/20039384?wl_ref=list_ab_04\" class=\"artistTitle\" title=\"네인\" onclick=\"\n\" target=\"_self\">네인</a>\n</p>\n<p>\n<time datetime=\"\">2024.11.25</time>\n<span class=\"albumType\">싱글</span>\n</p>","link":"https://music.bugs.co.kr/album/20687186?wl_ref=list_ab_03","retrieved":1732530274220,"image":"https://image.bugsm.co.kr/album/images/170/206871/20687186.jpg?version=1732525234000"},{"title":"시와 노래","contents":"<p class=\"artist\">\n<a href=\"https://music.bugs.co.kr/artist/20223923?wl_ref=list_ab_04\" class=\"artistTitle\" title=\"라지오\" onclick=\"\n\" target=\"_self\">라지오</a>\n</p>\n<p>\n<time datetime=\"\">2024.11.25</time>\n<span class=\"albumType\">싱글</span>\n</p>","link":"https://music.bugs.co.kr/album/20687182?wl_ref=list_ab_03","retrieved":1732508822740,"image":"https://image.bugsm.co.kr/album/images/170/206871/20687182.jpg?version=1732503632000"},{"title":"행복한 꿈","contents":"<p class=\"artist\">\n<a href=\"https://music.bugs.co.kr/artist/20120392?wl_ref=list_ab_04\" class=\"artistTitle\" title=\"O.SUN (영선)\" onclick=\"\n\" target=\"_self\">O.SUN (영선)</a>\n</p>\n<p>\n<time datetime=\"\">2024.11.25</time>\n<span class=\"albumType\">싱글</span>\n</p>","link":"https://music.bugs.co.kr/album/20687176?wl_ref=list_ab_03","retrieved":1732508822741,"image":"https://image.bugsm.co.kr/album/images/170/206871/20687176.jpg?version=1732503632000"},{"title":"예수를 나의 구주삼고","contents":"<p class=\"artist\">\n<a href=\"https://music.bugs.co.kr/artist/20223913?wl_ref=list_ab_04\" class=\"artistTitle\" title=\"HolyLand\" onclick=\"\n\" target=\"_self\">HolyLand</a>\n</p>\n<p>\n<time datetime=\"\">2024.11.25</time>\n<span class=\"albumType\">싱글</span>\n</p>","link":"https://music.bugs.co.kr/album/20687171?wl_ref=list_ab_03","retrieved":1732508822743,"image":"https://image.bugsm.co.kr/album/images/170/206871/20687171.jpg?version=1732554137000"},{"title":"후반전 내인생","contents":"<p class=\"artist\">\n<a href=\"https://music.bugs.co.kr/artist/20223915?wl_ref=list_ab_04\" class=\"artistTitle\" title=\"박영기\" onclick=\"\n\" target=\"_self\">박영기</a>\n</p>\n<p>\n<time datetime=\"\">2024.11.25</time>\n<span class=\"albumType\">싱글</span>\n</p>","link":"https://music.bugs.co.kr/album/20687169?wl_ref=list_ab_03","retrieved":1732508822745,"image":"https://image.bugsm.co.kr/album/images/170/206871/20687169.jpg?version=1732503632000"},{"title":"BDMG : Christmas Edition 2024","contents":"<p class=\"artist\">\n<!-- a tag title -->\n<a href=\"https://music.bugs.co.kr/artist/20211513?wl_ref=list_ab_04\" class=\"artistTitle\" title=\"SONS\">SONS</a>\n<!-- a tag link -->\n<a href=\"javascript:void(0);\" name=\"atag_martist_list\" class=\"more\" title=\"아티스트 전체보기\" wise_log_str=\"?wl_ref=list_ab_04\" onclick=\"bugs.layermenu.openMultiArtistSearchResultPopLayer(this, 'SONS||SONS||20211513||OK\\\\nSIROO (강승호)||SIROO (강승호)||20199115||OK\\\\nJZJZ||JZJZ||20211511||OK\\\\nNOAH (천우경)||NOAH (천우경)||20010168||OK', ''); return false;\">\nSONS\n</a> </p>\n<p>\n<time datetime=\"\">2024.11.25</time>\n<span class=\"albumType\">싱글</span>\n</p>","link":"https://music.bugs.co.kr/album/20687155?wl_ref=list_ab_03","retrieved":1732508822746,"image":"https://image.bugsm.co.kr/album/images/170/206871/20687155.jpg?version=1732503632000"},{"title":"새로운 시작","contents":"<p class=\"artist\">\n<a href=\"https://music.bugs.co.kr/artist/20223909?wl_ref=list_ab_04\" class=\"artistTitle\" title=\"Wave me worship\" onclick=\"\n\" target=\"_self\">Wave me worship</a>\n</p>\n<p>\n<time datetime=\"\">2024.11.25</time>\n<span class=\"albumType\">싱글</span>\n</p>","link":"https://music.bugs.co.kr/album/20687154?wl_ref=list_ab_03","retrieved":1732508822748,"image":"https://image.bugsm.co.kr/album/images/170/206871/20687154.jpg?version=1732503632000"},{"title":"불나방","contents":"<p class=\"artist\">\n<a href=\"https://music.bugs.co.kr/artist/20221935?wl_ref=list_ab_04\" class=\"artistTitle\" title=\"사실무근\" onclick=\"\n\" target=\"_self\">사실무근</a>\n</p>\n<p>\n<time datetime=\"\">2024.11.25</time>\n<span class=\"albumType\">싱글</span>\n</p>","link":"https://music.bugs.co.kr/album/20687100?wl_ref=list_ab_03","retrieved":1732508822752,"image":"https://image.bugsm.co.kr/album/images/170/206871/20687100.jpg?version=1732503632000"},{"title":"바보 멍청이","contents":"<p class=\"artist\">\n<a href=\"https://music.bugs.co.kr/artist/20211244?wl_ref=list_ab_04\" class=\"artistTitle\" title=\"필헌\" onclick=\"\n\" target=\"_self\">필헌</a>\n</p>\n<p>\n<time datetime=\"\">2024.11.25</time>\n<span class=\"albumType\">싱글</span>\n</p>","link":"https://music.bugs.co.kr/album/20687088?wl_ref=list_ab_03","retrieved":1732508822753,"image":"https://image.bugsm.co.kr/album/images/170/206870/20687088.jpg?version=1732552537000"},{"title":"오늘이 지나면 우리는 남이 될 거야","contents":"<p class=\"artist\">\n<a href=\"https://music.bugs.co.kr/artist/20117417?wl_ref=list_ab_04\" class=\"artistTitle\" title=\"박호경\" onclick=\"\n\" target=\"_self\">박호경</a>\n</p>\n<p>\n<time datetime=\"\">2024.11.25</time>\n<span class=\"albumType\">싱글</span>\n</p>","link":"https://music.bugs.co.kr/album/20686973?wl_ref=list_ab_03","retrieved":1732508822755,"image":"https://image.bugsm.co.kr/album/images/170/206869/20686973.jpg?version=1732553625000"}]}